<?xml version="1.0" encoding="utf-8" ?><dwsync><file name="cacatua.jpg" server="93.188.160.104/curso/" local="3529330242" remote="3592596240" Dst="-1" /><file name="camaleon.jpg" server="93.188.160.104/curso/" local="3529330242" remote="3592596240" Dst="-1" /><file name="canario.jpg" server="93.188.160.104/curso/" local="3529330244" remote="3592596240" Dst="-1" /><file name="cascabel.jpg" server="93.188.160.104/curso/" local="3529330246" remote="3592596240" Dst="-1" /><file name="conejo.jpg" server="93.188.160.104/curso/" local="3529330246" remote="3592596240" Dst="-1" /><file name="cuyo.jpg" server="93.188.160.104/curso/" local="3529330248" remote="3592596240" Dst="-1" /><file name="gato.jpg" server="93.188.160.104/curso/" local="3529330248" remote="3592596240" Dst="-1" /><file name="hamster.jpg" server="93.188.160.104/curso/" local="3529330250" remote="3592596240" Dst="-1" /><file name="huron.jpg" server="93.188.160.104/curso/" local="3529330252" remote="3592596240" Dst="-1" /><file name="iguana.jpg" server="93.188.160.104/curso/" local="3529330252" remote="3592596240" Dst="-1" /><file name="lagartija.jpg" server="93.188.160.104/curso/" local="3529330254" remote="3592596240" Dst="-1" /><file name="loro.jpg" server="93.188.160.104/curso/" local="3529330254" remote="3592596240" Dst="-1" /><file name="mapache.jpg" server="93.188.160.104/curso/" local="3529330256" remote="3592596240" Dst="-1" /><file name="mariposa.jpg" server="93.188.160.104/curso/" local="3529330256" remote="3592596240" Dst="-1" /><file name="pato.jpg" server="93.188.160.104/curso/" local="3529330258" remote="3592596240" Dst="-1" /><file name="perico.jpg" server="93.188.160.104/curso/" local="3529330258" remote="3592596240" Dst="-1" /><file name="perro.jpg" server="93.188.160.104/curso/" local="3529330260" remote="3592596240" Dst="-1" /><file name="pez.jpg" server="93.188.160.104/curso/" local="3529330260" remote="3592596240" Dst="-1" /><file name="piton.jpg" server="93.188.160.104/curso/" local="3529330262" remote="3592596240" Dst="-1" /><file name="rana.jpg" server="93.188.160.104/curso/" local="3529330262" remote="3592596240" Dst="-1" /><file name="raton.jpg" server="93.188.160.104/curso/" local="3529330264" remote="3592596240" Dst="-1" /><file name="sapo.jpg" server="93.188.160.104/curso/" local="3529330264" remote="3592596240" Dst="-1" /><file name="tarantula.jpg" server="93.188.160.104/curso/" local="3529330266" remote="3592596240" Dst="-1" /><file name="tucan.jpg" server="93.188.160.104/curso/" local="3529330268" remote="3592596240" Dst="-1" /><file name="tortuga.jpg" server="93.188.160.104/curso/" local="3529330266" remote="3592596240" Dst="-1" /></dwsync>